<?xml version="1.0" encoding="UTF-8" standalone="no"?>
<!--
 * 
-->
<pk><wd nm="off" rd="0,0:2146|14,0:481|30,0:211|54,0:3469|65,0:601,736,1545,1968|72,0:496|73,0:537|74,0:967,2620|81,64:240,537,1675|102,0:343|119,0:1650|121,0:1722,1761,1805|126,0:1371|127,128:7,86,117,330,407,425,987"/><wd nm="off/on" rd="30,64:3173|81,64:1908"/><wd nm="offer" rd="96,0:324"/><wd nm="offic" rd="4,0:3508|13,0:3138|33,0:365|96,0:2375|104,0:1729|118,0:167,283,597|119,0:3410"/><wd nm="offlin" rd="58,0:134,483|121,0:280|133,128:7,77,269,287,567,637,792,920,2149,2263"/><wd nm="offline," rd="133,64:2027"/><wd nm="often" rd="34,0:2515|119,0:6429|125,0:1078|126,0:1249|131,0:1096|132,0:1096"/><wd nm="ok" rd="0,0:1278,1902|6,0:683,833,1232|7,0:447,526|8,0:605,623|10,0:490|15,0:1004,1230|16,0:852|23,0:1053|24,0:471,550|28,0:933,951|32,0:347|41,0:450|47,0:438|53,0:1524,2621|62,0:643|64,0:750|69,0:336|91,0:463|98,0:1757,2384,2934|100,0:848|103,0:841|107,0:485|109,0:228|112,0:342|121,0:1677|129,0:357|135,0:1593"/><wd nm="old" rd="31,0:507,516,564,685,1150|83,0:681|112,0:673"/><wd nm="older" rd="31,0:1155"/><wd nm="oldest" rd="30,0:1122|31,0:623|122,0:1048"/><wd nm="omit" rd="52,0:938"/><wd nm="on" rd="0,0:586,1552,2064|1,0:726,1120,1145,1254,1306,1364,1835,1899|2,0:164,275,381|4,0:162,742,767,1902,3240,3970,3991|5,0:169,204|6,0:254,522,750,880,1213|9,0:174,239,338,644,764|10,0:225,264,412,492|11,128:25,118,226,291,882|12,0:858,1511,2174,2467|13,0:730,755,1556,2870,3600,3621|15,0:238,353,793,841,1064,1111|16,0:185,375,876|17,0:2873,3056,3496,3598,3647,3679,3731|19,0:699|20,64:1109,1260,2463|21,0:595,1255,1274|22,0:184,241,496|23,0:639,978|25,0:328|29,0:216,348|30,0:245,297,555,1058|33,0:381,540,567,817,992,1140,1238,1649|34,0:360,374,584,803,1002|35,0:355,883,1195,1483|36,0:275,412,600,612,1146,1450|37,0:549|38,0:269,739|39,0:350,1050|40,0:766|43,0:1833|47,0:280|49,0:253,377,827|50,0:192,251,354|51,0:201,529,1072|53,0:1076,1433,1598,1724,2451|54,0:2061,2951,3400,3465|55,0:764,866,911|56,0:240,279,362,449,590,743|58,0:592,620,2225|59,0:620,714|60,0:145,294|61,0:154,169,323,674,827|63,0:569|65,0:298,405,527,597,657,701,864,891,984,1037,1341,1438,1487,1541,1601,1645,1760,1861,1910,1964,2024,2068|66,0:287|67,0:1245|71,0:266,294,763|72,0:375,454|73,0:397,422|74,0:326,569,665,737,912,2603|75,0:127|76,0:145,180|77,0:513|78,0:261,406,580,742|81,64:226,243,384,419,470,483,605,664,754,1154,1671|83,0:709,1672|84,0:251|87,0:545|89,0:5910|90,0:688,1376,1401,1466|91,0:286|98,0:479,1791|99,0:303|100,0:493|101,0:113|102,0:339|103,0:753|104,0:1004,1023,1152,1529,1638|105,0:375,472,711,1875|106,0:146,201,393,510|108,0:212,235|110,0:134|116,0:751,1007|118,0:647|119,0:234,297,443,652,1239,1367,1380|121,0:354,683,1290,1507,1563,1764,1968|122,0:274,889,1280,1417|124,0:157,452|125,0:1213|127,0:373,595,651|128,128:20,482,899,1545|129,0:122,329|130,0:2170|131,0:1231|132,0:892,1234|133,0:835|134,0:258|135,0:438,567,794,959|136,0:716,1236,1371,1604,1720,1874,2677|137,0:357,601,733,923,1052|138,0:265,364,453,547|139,0:108" sp="1"/><wd nm="onc" rd="0,0:1682|26,0:515|31,0:224|33,0:1404|41,0:228|43,0:1061|61,0:531|100,32:1042|102,0:351|118,0:350"/><wd nm="one" rd="1,0:1103,1404|2,0:235|3,0:298|4,0:884,1860|6,2:169,720|10,0:171,227|12,0:758|13,0:872|16,0:705|17,0:2849,3241,3338|20,0:720|22,0:110|23,0:780|30,0:560,2403|31,0:1278,1468,1782,2005|33,0:1437,1615|34,0:544,2320|38,0:707|39,0:937|42,0:278|43,0:1080|44,0:731|48,0:647,696|52,0:2183,3266|53,0:1293,2091|54,0:775,902,975,1021,1647,1830,2522|55,0:564|56,0:259|58,0:190,1071,2189|59,1:102,569|61,0:211,249,301,357,676,813|63,0:465|64,0:397,449|69,0:173|74,0:159|79,0:108,349|86,0:156,880|89,0:2031,2682,3792,4239|90,0:836|92,0:795,1366|93,0:202|95,32:181,825,868,1467|96,0:448,995|98,0:1049,2473|99,0:607,656|100,0:996,1122|103,0:264|106,0:350,459|109,0:108|110,0:171|113,0:163,796|116,0:1053|119,0:1203,3589,5372|123,0:299,809|128,0:214|134,0:181|137,0:405,1302,1351"/><wd nm="ongo" rd="83,0:892"/><wd nm="onlin" rd="99,0:222|123,0:624|126,0:1185|133,0:877|136,0:1772,1996|137,0:255"/><wd nm="only" rd="6,0:293,824,1057|12,0:1986|14,0:124|17,0:558,1718,1956,1968,2474,2544|20,0:1317|29,0:328|31,0:220,1684|34,0:1745,2633|36,0:1130|39,0:142|46,0:159|47,0:144|48,0:146|52,0:635,1869,3262|53,0:1707|59,0:1747,1852,1902|65,0:479|77,0:351|82,0:206|83,0:196,537,1745|86,0:930|87,0:763|88,0:747|89,0:2730|90,0:940|93,0:350|95,0:305|96,0:1446|100,0:660|104,0:1910|112,0:1083|114,0:139|115,0:119|118,0:130,346|119,0:3134,4375,4422|122,0:211,994|125,0:2006|127,0:268|128,0:498|129,0:573|130,0:371|133,0:1738|135,0:128|136,0:134|137,0:147" sp="1"/><wd nm="onto" rd="100,0:482"/><wd nm="on th" rd="0,0:807"/><wd nm="open" rd="0,0:1536|1,0:1348,1857,1935|3,0:253|6,0:289,324,362|7,0:475|12,0:553|14,0:273|15,0:877,1147|16,0:281,328,954|17,0:962|20,0:461,1452,1648|23,32:110,126,511,586,845|24,0:499|25,0:450|30,0:1630|31,0:1665|33,0:295,416,498,868|34,0:118,289,728,1224,1778,1959,2292,2426,2704|36,0:289,382,497,526,560|37,0:522,595|39,0:268,815|40,0:742|41,0:493|46,0:555|48,0:273,365|50,0:400|53,0:490|58,0:786,944|59,0:1339,2033,2359,2819|60,0:228,372|61,0:374|62,0:702,809|64,0:566|65,0:191,1124|67,0:582,613|74,2:109,1619,1774,1972|76,0:729|77,0:113,378|78,128:0,78,400,471,666,913,1207,1687,1820,2378|80,0:644|82,0:170|83,0:305,644,1216|85,0:524,573|86,0:324,801|87,0:121,183,568,778|89,0:2603|91,0:319|92,0:419,704,1045,1327|93,0:878|95,0:1521|96,0:809|99,0:201,323|104,0:931|105,0:134,221,288,335,626,1174|106,0:94,224|107,0:228|109,0:316|113,0:836|115,0:290|116,0:215|117,0:479|119,0:1416,1894,1956,2517,2634,3007,3940,4062|122,0:1171|125,0:200,533,2406|128,0:674,821,1083|129,0:191|130,0:477,2687|131,0:190,551,1889|132,0:216,364,1702"/><wd nm="operation" rd="49,0:401,597"/><wd nm="operator" rd="52,0:551,1050,1734|55,0:145|89,0:363,407,495,510,593,621,719"/><wd nm="opt" rd="34,0:1381"/><wd nm="option" rd="3,1:82|4,0:586,3984|6,0:515,648|13,0:528,1307,3614|16,0:298,929|17,0:466,1046,1067|35,0:749|36,0:1139,1443|39,0:339,543|51,0:872|52,0:483,581,752,1261,1327|53,0:1054|54,0:3405|59,2:1026|71,0:651|74,0:2115|76,0:417|83,0:459,924,1665,1702|85,0:792|86,0:968|88,1:107,207|89,0:2768|93,0:427|95,0:382|96,0:1070|98,0:892,975,2208|100,0:792,920,1162|105,0:1537|112,0:387|114,0:166|116,0:304,970,1070|130,0:1852|132,0:1028|133,0:1525|134,0:189|135,0:642|136,0:1452"/><wd nm="option," rd="118,64:1117"/><wd nm="optional" rd="4,0:2549,2643,2732,2788|13,0:2179,2273,2362,2418|17,64:4340|37,0:757|46,0:670|74,0:1571|123,0:204|125,0:933|130,0:877|131,0:951"/><wd nm="options," rd="114,64:923"/><wd nm="or" rd="0,0:159,392,1027,1234,2333|1,0:139,512,1279,1388,1460,1726|4,0:239,1157,1335,1372,1459,1628,1713,2682,3501,3704,3774|6,0:182,320|8,64:376,568,1121|9,0:396|12,0:351,612,703,1258,1430,1578,1641,1678,2006|13,0:201,2312,3131,3334,3404|15,0:222,282,488,811|16,0:230,369,521,658,708,915|17,0:1093,2668|19,0:244|20,0:170,262,548,825,1239|21,0:977,1230|22,0:673|23,0:226,236,305,378|26,0:542|27,0:289|28,0:890|29,1:92,137,275|30,0:155,234,354,1135,1355,1634,1740,2090,2137,2234,2365|31,0:510,1153,1872|33,0:483,872,1365,1618|34,0:515,848,1475,1604,2056,2138,2311,2362,2444,2489,2547|35,0:210,265,407,981|36,0:163,502,658,784,1024,1184,1333|37,0:439,746|38,0:525,994,1276|39,0:412|40,0:212,778|41,0:560|42,0:179,287,838|43,0:232,1083,1306|44,0:514,754|46,0:260|47,0:174,349|48,0:416,443,562,610|49,0:754|51,0:1262,1513|52,0:384,660,685,969,1130,1299,1553,1897,2186,2271,2618|53,32:266,445,1122,1151,1259,1296,1392,1517|54,0:361,501,714,778,937,1120,1150,1183,1452,1498,1554,1833,1964,3105,3467|55,0:226,473,679,962|56,0:379,513,528,682,969|58,0:251,281,468,851,1691,1833,2251,2396|59,0:231,306,331,516,554,799|60,0:171|61,0:252,866|63,0:374|64,0:656,778|65,0:599,655,739,1155,1543,1599,1966,2022|66,0:453|67,0:151,684,876,1656|69,0:148|70,0:212|71,0:374,425,479,529,822,983,1029,1083|72,0:119,465,488|74,0:628,864,947,1839,2496,2509|77,0:215,349,400|78,0:222,384,670,1693|79,0:111|81,64:382,481,1007,1673|83,0:132,282,1024,1230,1538|85,0:133,363,689,774|86,128:5,80,181,358,448,490,611,934,1230,1637|87,0:360,547,850,884,912,948,1019,1043,1097,1128,1158|88,0:673,784|89,0:2056,2244,2287,2409,2734,2970,3082,3108,3145,3641,3735,4178,4242,5133,5173,5442,5525,5566,5890|90,0:124,223,244,369,799,1092,1263|91,0:211|92,0:369,802,843|93,128:26,123,173,258,618,758,1131,1637|94,128:26,134,198,478,858|95,1:104,155,213,705,871,1054,1113,1434,1477,1575,1770|96,0:208,259,1183,2404,2439,2616,2648|98,0:209,639,1474,1571,1851,1932,1979|99,0:301,374,401,517,570|100,0:304,590,607,999,1091,1196|102,0:232,266,341,391|103,0:759,992|104,0:275,535,1002,1443,1840,1887|105,0:126,685,1047,1335,1641,1711|106,0:174,353,462|109,0:207|110,0:345|112,0:319|113,0:140,545,806|115,0:228|116,0:463,1351|117,0:858,1039|119,0:747,1206,1360,1458,1543,2218,2351,2599,3370,3619,3736,4366,4566,4813,5135,5756,6182,6400,6704,6935,7083|122,0:1339|123,0:145,202,302,378,589,979,1461|125,0:322|126,0:281,896|127,0:266|130,0:265,352|133,0:1042|134,0:230|135,0:176,198,776,1014,1114|136,0:955,1005,1586,2469|137,16:355,820,1217,1265,1613,1871,1934,2046,2174,2399,2639|138,0:425,561|139,0:441" sp="1"/><wd nm="orang" rd="17,0:3275"/><wd nm="order" rd="27,0:219|28,0:675,746|30,0:2353,2377|31,0:415,485,695|36,0:752|43,0:1232|53,0:830|54,4:1754,2903,2933,2990,3170,3305|86,0:741|89,0:2542|100,0:198|128,128:15,737,1540"/><wd nm="organiz" rd="0,0:519|24,0:610|59,0:2923|63,0:424|104,0:217|123,0:415,448,856|128,1:85"/><wd nm="organization" rd="0,0:2226,2254|4,0:405|13,0:347|17,0:277|26,0:347|98,0:183"/><wd nm="organizer" rd="9,0:724|11,0:151,271,341|12,0:1187,1240"/><wd nm="origin" rd="84,0:152"/><wd nm="original" rd="0,0:574,652|22,0:852|30,0:884|37,0:348,465|42,0:414|69,0:620|71,0:604|83,0:216,579,937,1324,1619|84,0:274|108,0:417|119,0:3216,4217,4277,4594,4728"/><wd nm="other" rd="0,0:1722,2214|1,0:501,828|4,0:806,1341,1465,1634|9,0:314|13,0:794|17,0:836|19,0:392|20,0:569,845|21,0:716|30,0:1239|31,0:1548|33,0:371|39,0:1059|42,0:668|43,0:2324|44,0:419|50,0:236|52,0:687,2816,2850,3195|54,0:643|55,0:1030|58,0:242|59,0:308,801,1892|60,0:308,420|63,0:376|64,0:216|67,0:1800|73,0:296|74,0:2437|78,0:227,431|79,0:539|80,0:173|81,0:172|82,0:524|83,0:250|85,0:733|87,0:950|89,0:565,2145|90,0:1094,1265|92,0:1422|93,0:620,1043,1175|95,0:1482,1682,1814|98,0:165,604,663|100,1:105,389|102,0:298|104,0:201,1712|113,0:537|119,0:4401,5381|121,2:1217,1241|122,0:276|123,0:952,1140|126,0:1019,1296|128,0:282|133,0:459,1690|134,0:631,698|135,0:624|136,0:189,853,1434|137,0:796,1109,1850,2129,2369,2610,2831|138,0:597" sp="1"/></pk>